{
  "name": "Level 5: Precision Leap",
  "start": { "x": 50, "y": 500 },
  "platforms": [
    { "x": 0, "y": 550, "w": 100, "h": 50 },
    { "x": 250, "y": 500, "w": 40, "h": 100 },
    { "x": 450, "y": 450, "w": 40, "h": 100 },
    { "x": 650, "y": 400, "w": 40, "h": 100 },
    { "x": 850, "y": 350, "w": 40, "h": 100 },
    { "x": 1050, "y": 300, "w": 200, "h": 50 }
  ],
  "spikes": [
    { "x": 150, "y": 550 },
    { "x": 350, "y": 550 },
    { "x": 550, "y": 550 },
    { "x": 750, "y": 550 },
    { "x": 950, "y": 550 }
  ],
  "goal": { "x": 1150, "y": 250 }
}
